{
  "kepler_7b": {
    "Restrela": 1.78,
    "Mestrela": 1.41,
    "RplanetaEarth": 18.18,
    "MplanetaEarth": 140,
    "EixoMaiorPlaneta": 0.06067,
    "Excentricidade": 0.026,
    "t_gyr": 3.5
  },
  "kepler-8_b": {
    "Restrela": 1.486,
    "Mestrela": 1.213,
    "RplanetaEarth": 15.905571,
    "MplanetaEarth": 177.9848,
    "EixoMaiorPlaneta": 0.04835,
    "Excentricidade": 0.18,
    "t_gyr": 3.8
  },
    "toi-733_b": {
    "Restrela": 0.9549,
    "Mestrela": 0.9560,
    "RplanetaEarth": 1.992,
    "MplanetaEarth": 5.72,
    "EixoMaiorPlaneta": 0.0618,
    "Excentricidade": 0.046,
    "t_gyr": 4.4
  }
}